forexrateapi/__init__.py
forexrateapi/client.py
forexrateapi-1.1.2.dist-info/METADATA
forexrateapi-1.1.2.dist-info/WHEEL
forexrateapi-1.1.2.dist-info/top_level.txt
forexrateapi-1.1.2.dist-info/RECORD
