Metadata-Version: 2.2
Name: forexrateapi
Version: 1.1.2
Summary: Official Python wrapper for forexrateapi.com
Home-page: https://github.com/forexrateapi/forexrateapi-python
Author: ForexRateAPI
Author-email: contact@forexrateapi.com
Keywords: currency,foreign exchange rate,currency conversion,exchangerate,rates
Requires-Dist: requests>=2.31.0
Dynamic: author
Dynamic: author-email
Dynamic: description
Dynamic: description-content-type
Dynamic: home-page
Dynamic: keywords
Dynamic: requires-dist
Dynamic: summary
